chatty_debug/__init__.py
chatty_debug/__main__.py
chatty_debug/debugger.py
chatty_debug/suggestions.py
chatty_debug-1.1.0.dist-info/LICENSE
chatty_debug-1.1.0.dist-info/METADATA
chatty_debug-1.1.0.dist-info/WHEEL
chatty_debug-1.1.0.dist-info/RECORD
