Metadata-Version: 2.1
Name: chatty-debug
Version: 1.1.0
Summary: Package for debugging python using ChatGPT
Home-page: https://github.com/danb27/chatty-debug
License: MIT
Keywords: chatgpt,debugging,optimization,refactoring
Author: danb27
Author-email: danbianchini@outlook.com
Requires-Python: >=3.9,<4.0
Classifier: License :: OSI Approved :: MIT License
Classifier: Programming Language :: Python :: 3
Classifier: Programming Language :: Python :: 3.9
Classifier: Programming Language :: Python :: 3.10
Classifier: Programming Language :: Python :: 3.11
Requires-Dist: chat-toolkit (==1.1.1)
Requires-Dist: colorama (>=0.4.6,<0.5.0)
Project-URL: Repository, https://github.com/danb27/chatty-debug
